shecan/__init__.py
shecan/api.py
shecan/cli.py
shecan/db.py
shecan/log.py
shecan/utils.py
shecan-0.4.2.dist-info/LICENSE
shecan-0.4.2.dist-info/METADATA
shecan-0.4.2.dist-info/WHEEL
shecan-0.4.2.dist-info/entry_points.txt
shecan-0.4.2.dist-info/top_level.txt
shecan-0.4.2.dist-info/RECORD
