Metadata-Version: 2.1
Name: shecan
Version: 0.4.2
Summary: 'The Shecan CLI is used to configure your DNS configuration based on Shecan website from the command line.'
Home-page: https://github.com/GreatBahram/Shecan-cli/
Author: Bahram Aghaei
Author-email: aghaee.bahram@gmail.com
License: Academic Free License, version 3
Project-URL: Source Code, https://github.com/GreatBahram/shecan-cli
Project-URL: Change Log, https://github.com/GreatBahram/shecan-cli/blob/master/CHANGES.md
Platform: UNKNOWN
Classifier: Programming Language :: Python :: 3 :: Only
Classifier: Programming Language :: Python :: 3.6
Classifier: Programming Language :: Python :: 3.7
Requires-Python: >=3.6
Requires-Dist: bs4
Requires-Dist: lxml
Requires-Dist: tabulate
